pymsgprompt/__init__.py
pymsgprompt/handler.py
pymsgprompt/logger.py
pymsgprompt/prompt.py
pymsgprompt/version.py
PyMsgPrompt-1.3.0.dist-info/LICENSE
PyMsgPrompt-1.3.0.dist-info/METADATA
PyMsgPrompt-1.3.0.dist-info/WHEEL
PyMsgPrompt-1.3.0.dist-info/top_level.txt
PyMsgPrompt-1.3.0.dist-info/RECORD
