Metadata-Version: 2.1
Name: PyMsgPrompt
Version: 1.3.0
Summary: PyMsgPrompt is a python module to embed prompt functionality in your code.         Current Version of the module is 1.3.0     
Home-page: https://github.com/antaripchatterjee/PyMsgPrompt
Author: Antarip Chatterjee
Author-email: antarip.chatterjee22@gmail.com
License: MIT
Platform: UNKNOWN
Classifier: License :: OSI Approved :: MIT License
Classifier: Operating System :: Microsoft :: Windows
Classifier: Operating System :: Unix
Classifier: Operating System :: POSIX :: Linux
Classifier: Operating System :: MacOS
Classifier: Operating System :: OS Independent
Classifier: Programming Language :: Python
Classifier: Programming Language :: Python :: 2
Classifier: Programming Language :: Python :: 3
Classifier: Environment :: Console
Classifier: Development Status :: 4 - Beta
Classifier: Intended Audience :: End Users/Desktop
Classifier: Intended Audience :: Developers
Classifier: Intended Audience :: Education
Classifier: Topic :: Education
Classifier: Topic :: Software Development
Classifier: Topic :: System :: Shells
